pytest_mockllm/__init__.py
pytest_mockllm/core.py
pytest_mockllm/fixtures.py
pytest_mockllm/plugin.py
pytest_mockllm/recording.py
pytest_mockllm/stats.py
pytest_mockllm/integrations/__init__.py
pytest_mockllm/integrations/langchain.py
pytest_mockllm/providers/__init__.py
pytest_mockllm/providers/anthropic.py
pytest_mockllm/providers/gemini.py
pytest_mockllm/providers/openai.py
pytest_mockllm-0.2.2.dist-info/METADATA
pytest_mockllm-0.2.2.dist-info/WHEEL
pytest_mockllm-0.2.2.dist-info/entry_points.txt
pytest_mockllm-0.2.2.dist-info/licenses/LICENSE
pytest_mockllm-0.2.2.dist-info/RECORD
