Metadata-Version: 2.4
Name: pytest-mockllm
Version: 0.2.2
Summary: 🚀 Zero-config pytest plugin for mocking LLM APIs - OpenAI, Anthropic, Gemini, LangChain & more
Project-URL: Homepage, https://www.dhirajdas.dev
Project-URL: Documentation, https://github.com/godhiraj-code/pytest-mockllm#readme
Project-URL: Repository, https://github.com/godhiraj-code/pytest-mockllm
Project-URL: Issues, https://github.com/godhiraj-code/pytest-mockllm/issues
Project-URL: Changelog, https://github.com/godhiraj-code/pytest-mockllm/blob/main/CHANGELOG.md
Author-email: Dhiraj Das <dhirajdas.666@gmail.com>
License-Expression: MIT
License-File: LICENSE
Keywords: ai,anthropic,api-mocking,artificial-intelligence,chatgpt,claude,gemini,gpt-4,gpt-4o,langchain,llama-index,llamaindex,llm,machine-learning,mock,mocking,nlp,openai,pytest,pytest-plugin,test-automation,test-fixtures,testing,unit-testing
Classifier: Development Status :: 4 - Beta
Classifier: Framework :: Pytest
Classifier: Intended Audience :: Developers
Classifier: License :: OSI Approved :: MIT License
Classifier: Operating System :: OS Independent
Classifier: Programming Language :: Python :: 3
Classifier: Programming Language :: Python :: 3.9
Classifier: Programming Language :: Python :: 3.10
Classifier: Programming Language :: Python :: 3.11
Classifier: Programming Language :: Python :: 3.12
Classifier: Programming Language :: Python :: 3.13
Classifier: Topic :: Scientific/Engineering :: Artificial Intelligence
Classifier: Topic :: Software Development :: Testing
Classifier: Topic :: Software Development :: Testing :: Mocking
Classifier: Topic :: Software Development :: Testing :: Unit
Classifier: Typing :: Typed
Requires-Python: >=3.9
Requires-Dist: pytest-asyncio>=0.23.0
Requires-Dist: pytest>=7.0.0
Provides-Extra: all
Requires-Dist: anthropic>=0.18.0; extra == 'all'
Requires-Dist: google-generativeai>=0.3.0; extra == 'all'
Requires-Dist: langchain-core>=0.1.0; extra == 'all'
Requires-Dist: openai>=1.0.0; extra == 'all'
Requires-Dist: tiktoken>=0.7.0; extra == 'all'
Provides-Extra: anthropic
Requires-Dist: anthropic>=0.18.0; extra == 'anthropic'
Provides-Extra: dev
Requires-Dist: mypy>=1.0.0; extra == 'dev'
Requires-Dist: pre-commit>=3.0.0; extra == 'dev'
Requires-Dist: pytest-cov>=4.0.0; extra == 'dev'
Requires-Dist: ruff>=0.1.0; extra == 'dev'
Requires-Dist: types-pyyaml>=6.0.0; extra == 'dev'
Provides-Extra: google
Requires-Dist: google-generativeai>=0.3.0; extra == 'google'
Provides-Extra: langchain
Requires-Dist: langchain-core>=0.1.0; extra == 'langchain'
Provides-Extra: openai
Requires-Dist: openai>=1.0.0; extra == 'openai'
Requires-Dist: tiktoken>=0.7.0; extra == 'openai'
